.VERSION
AUTHORS.rst
CONTRIBUTING.rst
HISTORY.rst
LICENSE
MANIFEST.in
Pipfile
Pipfile.lock
README.rst
USAGE.rst
dev-requirements.txt
requirements.txt
setup.cfg
setup.py
docs/Makefile
docs/authors.rst
docs/conf.py
docs/contributing.rst
docs/history.rst
docs/index.rst
docs/installation.rst
docs/modules.rst
docs/powermolelib.rst
docs/readme.rst
docs/usage.rst
powermolelib/.VERSION
powermolelib/AUTHORS.rst
powermolelib/CONTRIBUTING.rst
powermolelib/HISTORY.rst
powermolelib/LICENSE
powermolelib/Pipfile
powermolelib/Pipfile.lock
powermolelib/README.rst
powermolelib/USAGE.rst
powermolelib/__init__.py
powermolelib/_version.py
powermolelib/bootstrapagent.py
powermolelib/dev-requirements.txt
powermolelib/instructor.py
powermolelib/logging.py
powermolelib/miscellaneous.py
powermolelib/powermolelibexceptions.py
powermolelib/requirements.txt
powermolelib/transferagent.py
powermolelib/tunnel.py
powermolelib.egg-info/PKG-INFO
powermolelib.egg-info/SOURCES.txt
powermolelib.egg-info/dependency_links.txt
powermolelib.egg-info/not-zip-safe
powermolelib.egg-info/requires.txt
powermolelib.egg-info/top_level.txt
powermolelib/payload/agent.py
tests/test_powermolelib.py