Metadata-Version: 2.2
Name: powermolelib
Version: 3.4.11
Summary: a library that is responsible of modeling objects to connect to another host via one or more intermediaries, offering a variety of modes (FOR and TOR) and options (TRANSFER and COMMAND)
Home-page: https://github.com/yutanicorp/powermolelib
Author: Vincent Schouten
Author-email: powermole@protonmail.com
License: MIT
Keywords: powermole powermolelib ssh proxyjump hosts forwarding tor privacy
Classifier: Development Status :: 4 - Beta
Classifier: Intended Audience :: Developers
Classifier: License :: OSI Approved :: MIT License
Classifier: Natural Language :: English
Classifier: Programming Language :: Python :: 3.7
License-File: LICENSE
License-File: AUTHORS.rst
Requires-Dist: pexpect~=4.7.0
Requires-Dist: voluptuous~=0.11.7
Dynamic: author
Dynamic: author-email
Dynamic: classifier
Dynamic: description
Dynamic: home-page
Dynamic: keywords
Dynamic: license
Dynamic: requires-dist
Dynamic: summary
